{"chunk_definitions":[{"row":13,"row_count":1,"visible":true,"expansion_state":0,"options":{"engine":"r","label":"setup","include":false},"document_id":"15F4FFB3","chunk_id":"csetup_chunk","chunk_label":"setup"},{"row":42,"row_count":1,"visible":true,"expansion_state":0,"options":{"engine":"r","label":"unnamed-chunk-241"},"document_id":"15F4FFB3","chunk_id":"cmnvwqa5qr8zq","chunk_label":"unnamed-chunk-2"},{"row":73,"row_count":1,"visible":true,"expansion_state":0,"options":{"engine":"r","label":"unnamed-chunk-243"},"document_id":"15F4FFB3","chunk_id":"cqpxz21hl8q0p","chunk_label":"unnamed-chunk-3"},{"row":86,"row_count":1,"visible":true,"expansion_state":0,"options":{"engine":"r","label":"unnamed-chunk-248"},"document_id":"15F4FFB3","chunk_id":"cuxix6sex7fci","chunk_label":"unnamed-chunk-4"}],"doc_write_time":1667070974}